1:2 mux/2mux.v
module mux2(input wire i0, i1, j, output wire o);
  assign o = (j==0)?i0:i1;
endmodule

1:2 mux/2mux_tb.v
module mux_tb;
reg t_a,t_b,t_s;
wire t_o;

mux2 mux(.i0(t_a),.i1(t_b),.j(t_s),.o(t_o));

initial begin $dumpfile("2mux.vcd");
$dumpvars(0,mux_tb);
end

initial begin $monitor(t_a,t_b,t_s,t_o);

t_a=1'b1;
t_b=1'b0;
t_s=1'b0;
#10
t_a=1'b0;
t_b=1'b1;
t_s=1'b0;
#10
t_a=1'b1;
t_b=1'b0;
t_s=1'b1;
#10
t_a=1'b1;
t_b=1'b1;
t_s=1'b0;
#10
t_a=1'b0;
t_b=1'b0;
t_s=1'b1;
#10
t_a=1'b0;
t_b=1'b1;
t_s=1'b1;
#10
t_a=1'b1;
t_b=1'b0;
t_s=1'b1;
#10
t_a=1'b1;
t_b=1'b1;
t_s=1'b1;

end
endmodule

1:2 mux/2mux.vcd
$date
	Sun Sep 18 19:16:40 2022
$end
$version
	Icarus Verilog
$end
$timescale
	1s
$end
$scope module mux_tb $end
$var wire 1 ! t_o $end
$var reg 1 " t_a $end
$var reg 1 # t_b $end
$var reg 1 $ t_s $end
$scope module mux $end
$var wire 1 " i0 $end
$var wire 1 # i1 $end
$var wire 1 $ j $end
$var wire 1 ! o $end
$upscope $end
$upscope $end
$enddefinitions $end
#0
$dumpvars
0$
0#
1"
1!
$end
#10
0!
1#
0"
#20
1$
0#
1"
#30
1!
0$
1#
#40
0!
1$
0#
0"
#50
1!
1#
#60
0!
0#
1"
#70
1!
1#
