week-2/full_adder/full_adder.v
module full_adder(a,b,c,y,x);
input a,b,c;
output y,x;
assign y = ((!a&!b&c)|(!a&b&c)|(a&!b&!c)|(a&b&c));
assign x = ((a&b)|(a&c)|(b&c));
endmodule

2/full_adder_tb.v
module full_adder_tb; 
wire t_y, t_x;
reg t_a, t_b, t_c;
full_adder my_gate( .a(t_a), .b(t_b), .c(t_c), .y(t_y), .x(t_x));
initial 
begin 
	$dumpfile("full_adder_tb.vcd");
	$dumpvars(0, full_adder_tb);
	$monitor(t_a, t_b, t_c, t_y);
	$display("Sum Output");
	t_a = 1'b0;
	t_b = 1'b0;
	t_c = 1'b0;
	#5
	t_a = 1'b0;
	t_b = 1'b0;
	t_c = 1'b1;
	#5
	t_a = 1'b0;
	t_b = 1'b1;
	t_c = 1'b0;
	#5
	t_a = 1'b0;
	t_b = 1'b1;
	t_c = 1'b1;
	#5
	t_a = 1'b1;
	t_b = 1'b0;
	t_c = 1'b0;
	#5
	t_a = 1'b1;
	t_b = 1'b0;
	t_c = 1'b1;
	#5
	t_a = 1'b1;
	t_b = 1'b1;
	t_c = 1'b0;
	#5
	t_a = 1'b1;
	t_b = 1'b1;
	t_c = 1'b1;
	
	
	$monitor(t_a, t_b, t_c, t_x);
	
	#5
	t_a = 1'b0;
	t_b = 1'b0;
	t_c = 1'b0;
	$display("Carry Output");
	#5
	t_a = 1'b0;
	t_b = 1'b0;
	t_c = 1'b1;
	#5
	t_a = 1'b0;
	t_b = 1'b1;
	t_c = 1'b0;
	#5
	t_a = 1'b0;
	t_b = 1'b1;
	t_c = 1'b1;
	#5
	t_a = 1'b1;
	t_b = 1'b0;
	t_c = 1'b0;
	#5
	t_a = 1'b1;
	t_b = 1'b0;
	t_c = 1'b1;
	#5
	t_a = 1'b1;
	t_b = 1'b1;
	t_c = 1'b0;
	#5
	t_a = 1'b1;
	t_b = 1'b1;
	t_c = 1'b1;
end  
endmodule

week-2/full_adder/full_adder_tb.vcd
$date
	Sun Aug 28 12:53:36 2022
$end
$version
	Icarus Verilog
$end
$timescale
	1s
$end
$scope module full_adder_tb $end
$var wire 1 ! t_y $end
$var wire 1 " t_x $end
$var reg 1 # t_a $end
$var reg 1 $ t_b $end
$var reg 1 % t_c $end
$scope module my_gate $end
$var wire 1 # a $end
$var wire 1 $ b $end
$var wire 1 % c $end
$var wire 1 " x $end
$var wire 1 ! y $end
$upscope $end
$upscope $end
$enddefinitions $end
#0
$dumpvars
0%
0$
0#
0"
0!
$end
#5
1!
1%
#10
0!
0%
1$
#15
1!
1"
1%
#20
0"
0%
0$
1#
#25
1"
0!
1%
#30
0%
1$
#35
1!
1%
#40
0!
0"
0%
0$
0#
#45
1!
1%
#50
0!
0%
1$
#55
1!
1"
1%
#60
0"
0%
0$
1#
#65
1"
0!
1%
#70
0%
1$
#75
1!
1%
