8-bit Booth Multiplier/bit.v
module Booth_Multiplier(clock,reset,start,X,Y,valid,Z);

input clock;
input reset;
input start;

input signed [7:0]X,Y;
output signed [15:0]Z;
output valid;

reg signed [15:0] Z,next_Z,Z_temp;
reg next_state, present_state;
reg [2:0] temp,next_temp;
reg [2:0] count,next_count;
reg valid, next_valid;

parameter IDLE = 1'b0;
parameter START = 1'b1;

always @ (posedge clock or negedge reset)
begin
if(!reset)
   begin
   Z          <= 16'd0;
   valid      <= 1'b0;
   present_state <= 1'b0;
   temp       <= 2'd0;
   count      <= 2'd0;
   end

else
   begin
   Z          <= next_Z;
   valid      <= next_valid;
   present_state <= next_state;
   temp       <= next_temp;
   count      <= next_count;
   end
end

always @ (*)
begin 
case(present_state)

IDLE:
begin
next_count = 2'b0;
next_valid = 1'b0;
if(start)
   begin
      next_state = START;
      next_temp  = {X[0],1'b0};
      next_Z     = {8'd0,X};
   end
else
   begin
      next_state = present_state;
      next_temp  = 4'd0;
      next_Z     = 16'd0;
   end
end

START:
begin
    case(temp)
    4'b10:   Z_temp = {Z[15:8]-Y,Z[7:0]};
    4'b01:   Z_temp = {Z[15:8]+Y,Z[7:0]};
    default: Z_temp = {Z[15:8],Z[7:0]};
    endcase
next_temp  = {X[count+1],X[count]};
next_count = count + 1'b1;
next_Z     = Z_temp >>> 1;
next_valid = (&count) ? 1'b1 : 1'b0; 
next_state = (&count) ? IDLE : present_state;	
end
endcase
end
endmodule

8-bit Booth Multiplier/bit_tb.v
module booth_tb;

reg clock,reset,start;
reg signed [7:0]X,Y;
wire signed [15:0]Z;
wire valid;

always #5 clock = ~clock;

Booth_Multiplier inst (clock,reset,start,X,Y,valid,Z);

initial
$monitor($time,"X=%d, Y=%d, valid=%d, Z=%d ",X,Y,valid,Z);

initial
begin

X=-56;Y=-70;clock=1'b1;reset=1'b0;start=1'b0;
#10 reset = 1'b1;
#10 start = 1'b1;
#10 start = 1'b0;
#110 reset = 1'b0;
#120 clock = 1'b0;

$finish;
end     

initial 
begin

$dumpfile("Booth_Multiplier.vcd");
  $dumpvars(0,booth_tb);

end

endmodule

8-bit Booth Multiplier/Booth_Multiplier.vcd
$date
	Thu Oct 27 23:05:48 2022
$end
$version
	Icarus Verilog
$end
$timescale
	1s
$end
$scope module booth_tb $end
$var wire 1 ! valid $end
$var wire 16 " Z [15:0] $end
$var reg 8 # X [7:0] $end
$var reg 8 $ Y [7:0] $end
$var reg 1 % clock $end
$var reg 1 & reset $end
$var reg 1 ' start $end
$scope module inst $end
$var wire 8 ( X [7:0] $end
$var wire 8 ) Y [7:0] $end
$var wire 1 % clock $end
$var wire 1 & reset $end
$var wire 1 ' start $end
$var reg 16 * Z [15:0] $end
$var reg 16 + Z_temp [15:0] $end
$var reg 3 , count [2:0] $end
$var reg 16 - next_Z [15:0] $end
$var reg 3 . next_count [2:0] $end
$var reg 1 / next_state $end
$var reg 3 0 next_temp [2:0] $end
$var reg 1 1 next_valid $end
$var reg 1 2 present_state $end
$var reg 3 3 temp [2:0] $end
$var reg 1 ! valid $end
$upscope $end
$upscope $end
$enddefinitions $end
#0
$dumpvars
b0 3
02
01
b0 0
0/
b0 .
b0 -
b0 ,
bx +
b0 *
b10111010 )
b11001000 (
0'
0&
1%
b10111010 $
b11001000 #
b0 "
0!
$end
#5
0%
#10
1%
1&
#15
0%
#20
b1 .
b11001000 +
12
b11001000 "
b11001000 *
b1100100 -
1/
1%
1'
#25
0%
#30
b110010 -
b10 .
b1100100 +
b1 ,
b1100100 "
b1100100 *
1%
0'
#35
0%
#40
b11001 -
b11 .
b10 0
b110010 +
b10 ,
b110010 "
b110010 *
1%
#45
0%
#50
b10001100001100 -
b100 .
b1 0
b100011000011001 +
b11 ,
b10 3
b11001 "
b11001 *
1%
#55
0%
#60
b1110111010000110 -
b101 .
b0 0
b1101110100001100 +
b100 ,
b1 3
b10001100001100 "
b10001100001100 *
1%
#65
0%
#70
b1111011101000011 -
b110 .
b10 0
b1110111010000110 +
b101 ,
b0 3
b1110111010000110 "
b1110111010000110 *
1%
#75
0%
#80
b1111010100001 -
b111 .
b11 0
b11110101000011 +
b110 ,
b10 3
b1111011101000011 "
b1111011101000011 *
1%
#85
0%
#90
0/
11
b111101010000 -
b0 .
b0x1 0
b1111010100001 +
b111 ,
b11 3
b1111010100001 "
b1111010100001 *
1%
#95
0%
#100
b0 -
b0 0
01
b0 ,
b0x1 3
02
1!
b111101010000 "
b111101010000 *
1%
#105
0%
#110
b0 3
0!
b0 "
b0 *
1%
#115
0%
#120
1%
#125
0%
#130
1%
#135
0%
#140
1%
0&
