2/circuit-2/circuit2.v
module simple_circuit(A2,B2,C2,Y);

output Y;

input A2,B2,C2;

wire w1,w2,w3;

assign w1= C2&B2;
assign w2= A2|w1;
assign w3= B2&A2; 
assign Y=  w2|w3;
 
endmodule

2/circuit-2/tb_circuit2.v
module tb_simple_circuit;

reg A,B,C;

simple_circuit M1(A,B,C,Y);

initial

begin

A=1'b0 ; B=1'b0 ; C=1'b0;
#20
A=1'b0 ; B=1'b0 ; C=1'b1;
#20
A=1'b0 ; B=1'b1 ; C=1'b0;
#20
A=1'b0 ; B=1'b1 ; C=1'b1;
#20
A=1'b1 ; B=1'b0 ; C=1'b0;
#20
A=1'b1 ; B=1'b0 ; C=1'b1;
#20
A=1'b1 ; B=1'b1 ; C=1'b0;
#20
A=1'b1 ; B=1'b1 ; C=1'b1;

end


initial
begin
$monitor("A2=%b, B2=%b, C2=%b,Y=%b", A,B,C,Y);
end
initial
begin
$dumpfile ("circuit2.vcd");
 $dumpvars (0, tb_simple_circuit);
end
endmodule

2/circuit-2/circuit2.vcd
$date
	Tue Aug 30 19:54:53 2022
$end
$version
	Icarus Verilog
$end
$timescale
	1s
$end
$scope module tb_simple_circuit $end
$var wire 1 ! Y $end
$var reg 1 " A $end
$var reg 1 # B $end
$var reg 1 $ C $end
$scope module M1 $end
$var wire 1 " A2 $end
$var wire 1 # B2 $end
$var wire 1 $ C2 $end
$var wire 1 ! Y $end
$var wire 1 % w1 $end
$var wire 1 & w2 $end
$var wire 1 ' w3 $end
$upscope $end
$upscope $end
$enddefinitions $end
#0
$dumpvars
0'
0&
0%
0$
0#
0"
0!
$end
#20
1$
#40
0$
1#
#60
1!
1&
1%
1$
#80
0%
0$
0#
1"
#100
1$
#120
1'
0$
1#
#140
1%
1$
