week-2/half_adder/half_adder.v
module half_adder(a,b,y,x);
input a,b;
output y,x;
assign y = (a&!b)|(!a&b);
assign x = a&b;
endmodule

week-2/half_adder/half_adder_tb.v
module half_adder_tb; 
wire t_y, t_x;
reg t_a, t_b;
half_adder my_gate( .a(t_a), .b(t_b), .y(t_y), .x(t_x));
initial 
begin 
	$dumpfile("half_adder_tb.vcd");
	$dumpvars(0, half_adder_tb);
	$monitor("A=%b, B=%b, Y=%b", t_a, t_b, t_y);
	$display("Sum Output");
	t_a = 1'b0;
	t_b = 1'b0;
	#5
	t_a = 1'b0;
	t_b = 1'b1;
	#5
	t_a = 1'b1;
	t_b = 1'b0;
	#5
	t_a = 1'b1;
	t_b = 1'b1;
	
	$monitor( "A=%b, B=%b, Y=%b", t_a, t_b, t_x);
	
	#5
	t_a = 1'b0;
	t_b = 1'b0;
	$display("Carry Output");
	#5
	t_a = 1'b0;
	t_b = 1'b1;
	#5
	t_a = 1'b1;
	t_b = 1'b0;
	#5
	t_a = 1'b1;
	t_b = 1'b1;
end  
endmodule

week-2/half_adder/half_adder_tb.vcd
$date
	Tue Sep 13 17:04:47 2022
$end
$version
	Icarus Verilog
$end
$timescale
	1s
$end
$scope module half_adder_tb $end
$var wire 1 ! t_y $end
$var wire 1 " t_x $end
$var reg 1 # t_a $end
$var reg 1 $ t_b $end
$scope module my_gate $end
$var wire 1 # a $end
$var wire 1 $ b $end
$var wire 1 " x $end
$var wire 1 ! y $end
$upscope $end
$upscope $end
$enddefinitions $end
#0
$dumpvars
0$
0#
0"
0!
$end
#5
1!
1$
#10
0$
1#
#15
0!
1"
1$
#20
0"
0$
0#
#25
1!
1$
#30
0$
1#
#35
0!
1"
1$
